tube_scrapy/__init__.py
tube_scrapy/exceptions.py
tube_scrapy/scraped_video_info.py
tube_scrapy/test_tube_scrapy.py
tube_scrapy/tube_scrapy.py
tube_scrapy-1.0.0b3.dist-info/LICENSE
tube_scrapy-1.0.0b3.dist-info/METADATA
tube_scrapy-1.0.0b3.dist-info/WHEEL
tube_scrapy-1.0.0b3.dist-info/top_level.txt
tube_scrapy-1.0.0b3.dist-info/RECORD
