Metadata-Version: 2.1
Name: tube-scrapy
Version: 1.0.0b3
Summary: A python package to webscraping for youtube video data as title, video url, thumbnail url, and number of views.
Author-email: Abner Freitas <defreitasabner@gmail.com>
License: MIT License
Project-URL: Repository, https://github.com/defreitasabner/tube_scrapy
Project-URL: Issue Tracker, https://github.com/defreitasabner/tube_scrapy/issues
Project-URL: Changelog, https://github.com/defreitasabner/tube_scrapy/blob/main/CHANGELOG.md
Keywords: webscraping,youtube
Classifier: Development Status :: 4 - Beta
Classifier: Programming Language :: Python :: 3.8
Classifier: License :: OSI Approved :: MIT License
Classifier: Operating System :: OS Independent
Requires-Python: >=3.7
License-File: LICENSE
Requires-Dist: selenium
Requires-Dist: webdriver-manager
